buptgw/__init__.py
buptgw-0.1.1.dist-info/LICENSE
buptgw-0.1.1.dist-info/METADATA
buptgw-0.1.1.dist-info/WHEEL
buptgw-0.1.1.dist-info/entry_points.txt
buptgw-0.1.1.dist-info/top_level.txt
buptgw-0.1.1.dist-info/RECORD
