Metadata-Version: 2.1
Name: buptgw
Version: 0.1.1
Summary: login to gw.bupt.edu.cn to access the Internet
Home-page: https://github.com/sxwxs/buptGateway
Author: sxwxs
Author-email: sxwxs@msn.com
License: UNKNOWN
Project-URL: Bug Reports, https://github.com/sxwxs/buptGateway/issues
Project-URL: Funding, https://i.loli.net/2019/12/28/pv8PUd4eKGyNDiV.png
Project-URL: Source, https://github.com/sxwxs/buptGateway
Keywords: bupt network gateway login
Platform: UNKNOWN
Classifier: Development Status :: 4 - Beta
Classifier: Intended Audience :: End Users/Desktop
Classifier: Topic :: Utilities
Classifier: License :: OSI Approved :: MIT License
Classifier: Operating System :: OS Independent
Classifier: Programming Language :: Python :: 3
Classifier: Programming Language :: Python :: 3.5
Classifier: Programming Language :: Python :: 3.6
Classifier: Programming Language :: Python :: 3.7
Classifier: Programming Language :: Python :: 3.8
Requires-Python: >=3.5
Requires-Dist: requests
